cachez.py
cachez_test.py
cachez-0.1.2.dist-info/DESCRIPTION.rst
cachez-0.1.2.dist-info/METADATA
cachez-0.1.2.dist-info/RECORD
cachez-0.1.2.dist-info/WHEEL
cachez-0.1.2.dist-info/metadata.json
cachez-0.1.2.dist-info/top_level.txt
