Metadata-Version: 2.0
Name: cachez
Version: 0.1.2
Summary: Cache decorator for global or instance level memoize.
Home-page: http://github.com/jealous/cachez
Author: Cedric Zhuang
Author-email: jealous@163.com
License: Apache Software License
Keywords: cache decorator
Platform: any
Classifier: Programming Language :: Python
Classifier: Programming Language :: Python :: 2.7
Classifier: Programming Language :: Python :: 3.4
Classifier: Programming Language :: Python :: 3.5
Classifier: Programming Language :: Python :: Implementation :: CPython
Classifier: Programming Language :: Python :: Implementation :: PyPy
Classifier: Natural Language :: English
Classifier: Intended Audience :: Developers
Classifier: Operating System :: OS Independent
Classifier: Development Status :: 4 - Beta
Classifier: Topic :: Utilities
Classifier: License :: OSI Approved :: Apache Software License
